garpix_cloudpayments/MANIFEST.in
garpix_cloudpayments/README.md
garpix_cloudpayments/__init__.py
garpix_cloudpayments/apps.py
garpix_cloudpayments/setup.py
garpix_cloudpayments/urls.py
garpix_cloudpayments/utils.py
garpix_cloudpayments/__pycache__/__init__.cpython-38.pyc
garpix_cloudpayments/__pycache__/apps.cpython-38.pyc
garpix_cloudpayments/__pycache__/urls.cpython-38.pyc
garpix_cloudpayments/__pycache__/utils.cpython-38.pyc
garpix_cloudpayments/admin/__init__.py
garpix_cloudpayments/admin/config.py
garpix_cloudpayments/admin/payment.py
garpix_cloudpayments/admin/__pycache__/__init__.cpython-38.pyc
garpix_cloudpayments/admin/__pycache__/config.cpython-38.pyc
garpix_cloudpayments/admin/__pycache__/payment.cpython-38.pyc
garpix_cloudpayments/callbacks/__init__.py
garpix_cloudpayments/callbacks/empty_callback.py
garpix_cloudpayments/models/__init__.py
garpix_cloudpayments/models/choices.py
garpix_cloudpayments/models/config.py
garpix_cloudpayments/models/payment.py
garpix_cloudpayments/models/__pycache__/__init__.cpython-38.pyc
garpix_cloudpayments/models/__pycache__/choices.cpython-38.pyc
garpix_cloudpayments/models/__pycache__/config.cpython-38.pyc
garpix_cloudpayments/models/__pycache__/payment.cpython-38.pyc
garpix_cloudpayments/templates/garpix_cloudpayments/index.html
garpix_cloudpayments/views/__init__.py
garpix_cloudpayments/views/default_view.py
garpix_cloudpayments/views/fail.py
garpix_cloudpayments/views/pay.py
garpix_cloudpayments/views/payment_data.py
garpix_cloudpayments/views/__pycache__/__init__.cpython-38.pyc
garpix_cloudpayments-1.2.0.dist-info/METADATA
garpix_cloudpayments-1.2.0.dist-info/WHEEL
garpix_cloudpayments-1.2.0.dist-info/top_level.txt
garpix_cloudpayments-1.2.0.dist-info/RECORD
